orellm/__init__.py
orellm/built_in_type.py
orellm/class_.py
orellm/collection.py
orellm/example_types.py
orellm/type_.py
orellm-0.1.1.dist-info/LICENSE
orellm-0.1.1.dist-info/METADATA
orellm-0.1.1.dist-info/WHEEL
orellm-0.1.1.dist-info/top_level.txt
orellm-0.1.1.dist-info/RECORD
