Metadata-Version: 2.1
Name: orellm
Version: 0.1.1
Author: Richard Hayes
License-File: LICENSE
Requires-Dist: rellm
Requires-Dist: transformers
